src/Ui_window.py
src/__init__.py
src/config.py
src/globals.py
src/log.py
src/main.py
src/tftp/__init__.py
src/tftp/packet.py
src/tftp/server.py
usr/share/applications/HolyTFTP.desktop
usr/share/pixmaps/HolyTFTP.png
HolyTFTP-0.1.2.dist-info/LICENSE
HolyTFTP-0.1.2.dist-info/METADATA
HolyTFTP-0.1.2.dist-info/WHEEL
HolyTFTP-0.1.2.dist-info/entry_points.txt
HolyTFTP-0.1.2.dist-info/top_level.txt
HolyTFTP-0.1.2.dist-info/RECORD
